flifile/__init__.py
flifile/datatypes.py
flifile/flifile.py
flifile/py.typed
flifile/readheader.py
flifile/version.py
flifile-1.4.3.dist-info/LICENSE
flifile-1.4.3.dist-info/METADATA
flifile-1.4.3.dist-info/WHEEL
flifile-1.4.3.dist-info/top_level.txt
flifile-1.4.3.dist-info/RECORD
